{
  "lang":"en",
  "name":"pipeline",
  "version":"0.0.0",
  "spacy_version":">=3.8.14,<3.9.0",
  "description":"",
  "author":"",
  "email":"",
  "url":"",
  "license":"",
  "spacy_git_version":"0069cf9",
  "vectors":{
    "width":0,
    "vectors":0,
    "keys":0,
    "name":null,
    "mode":"default"
  },
  "labels":{
    "tok2vec":[

    ],
    "ner":[
      "ACCOUNTNAME",
      "ACCOUNTNUMBER",
      "AMOUNT",
      "BIC",
      "BITCOINADDRESS",
      "BUILDINGNUMBER",
      "CITY",
      "COUNTY",
      "CREDITCARDCVV",
      "CREDITCARDISSUER",
      "CREDITCARDNUMBER",
      "CURRENCY",
      "CURRENCYAMOUNT",
      "CURRENCYCODE",
      "CURRENCYNAME",
      "CURRENCYSYMBOL",
      "CURRENCY_N",
      "DISPLAYNAME",
      "EMAIL",
      "ETHEREUMADDRESS",
      "FIRSTNAME",
      "FULLNAME",
      "GENDER",
      "IBAN",
      "IP",
      "IPV4",
      "IPV6",
      "JOBAREA",
      "JOBDESCRIPTOR",
      "JOBTITLE",
      "JOBTYPE",
      "LASTNAME",
      "LITECOINADDRESS",
      "MAC",
      "MASKEDNUMBER",
      "NAME",
      "NEARBYGPSCOORDINATE",
      "NUMBER",
      "ORDINALDIRECTION",
      "PASSWORD",
      "PIN",
      "SEX",
      "STATE",
      "STREET",
      "STREETADDRESS",
      "URL",
      "USERAGENT",
      "USERNAME",
      "ZIPCODE"
    ]
  },
  "pipeline":[
    "tok2vec",
    "ner"
  ],
  "components":[
    "tok2vec",
    "ner"
  ],
  "disabled":[

  ],
  "performance":{
    "ents_f":0.9820239034,
    "ents_p":0.9737292853,
    "ents_r":0.9904610493,
    "ents_per_type":{
      "FULLNAME":{
        "p":0.9892546478,
        "r":0.9996552913,
        "f":0.9944277754
      },
      "NAME":{
        "p":0.9600833044,
        "r":0.9968465628,
        "f":0.9781196128
      },
      "EMAIL":{
        "p":0.9946153846,
        "r":0.9994846689,
        "f":0.9970440817
      },
      "FIRSTNAME":{
        "p":0.9863445378,
        "r":0.9952305246,
        "f":0.9907676075
      },
      "CITY":{
        "p":0.9916576964,
        "r":0.9964845863,
        "f":0.9940652819
      },
      "NUMBER":{
        "p":0.7944572748,
        "r":0.9885057471,
        "f":0.880921895
      },
      "ACCOUNTNUMBER":{
        "p":0.7803030303,
        "r":0.985645933,
        "f":0.8710359408
      },
      "ACCOUNTNAME":{
        "p":0.9941860465,
        "r":0.9941860465,
        "f":0.9941860465
      },
      "AMOUNT":{
        "p":0.9824561404,
        "r":1.0,
        "f":0.9911504425
      },
      "JOBAREA":{
        "p":0.9971498371,
        "r":1.0,
        "f":0.9985728848
      },
      "JOBTYPE":{
        "p":0.9836065574,
        "r":0.9836065574,
        "f":0.9836065574
      },
      "JOBTITLE":{
        "p":0.9954441913,
        "r":1.0,
        "f":0.997716895
      },
      "URL":{
        "p":0.9888641425,
        "r":0.9910714286,
        "f":0.9899665552
      },
      "GENDER":{
        "p":0.8985507246,
        "r":0.9738219895,
        "f":0.9346733668
      },
      "SEX":{
        "p":0.8043478261,
        "r":1.0,
        "f":0.8915662651
      },
      "STATE":{
        "p":0.9722479186,
        "r":1.0,
        "f":0.9859287054
      },
      "CURRENCYNAME":{
        "p":0.6831683168,
        "r":0.5847457627,
        "f":0.6301369863
      },
      "ZIPCODE":{
        "p":0.9852941176,
        "r":0.858974359,
        "f":0.9178082192
      },
      "USERAGENT":{
        "p":0.6869565217,
        "r":0.9875,
        "f":0.8102564103
      },
      "IPV4":{
        "p":0.9387755102,
        "r":0.9583333333,
        "f":0.9484536082
      },
      "IPV6":{
        "p":0.8153846154,
        "r":0.6235294118,
        "f":0.7066666667
      },
      "COUNTY":{
        "p":0.981981982,
        "r":1.0,
        "f":0.9909090909
      },
      "USERNAME":{
        "p":0.9043280182,
        "r":0.9589371981,
        "f":0.9308323564
      },
      "CREDITCARDNUMBER":{
        "p":0.975308642,
        "r":0.738317757,
        "f":0.8404255319
      },
      "CURRENCY":{
        "p":0.6201550388,
        "r":0.7272727273,
        "f":0.6694560669
      },
      "STREETADDRESS":{
        "p":0.9658703072,
        "r":0.9929824561,
        "f":0.9792387543
      },
      "CURRENCYCODE":{
        "p":0.9242424242,
        "r":0.9682539683,
        "f":0.9457364341
      },
      "IP":{
        "p":0.5945945946,
        "r":0.6666666667,
        "f":0.6285714286
      },
      "JOBDESCRIPTOR":{
        "p":0.9473684211,
        "r":0.9473684211,
        "f":0.9473684211
      },
      "BUILDINGNUMBER":{
        "p":0.9027777778,
        "r":0.9285714286,
        "f":0.9154929577
      },
      "CREDITCARDISSUER":{
        "p":0.95,
        "r":0.8260869565,
        "f":0.8837209302
      },
      "BITCOINADDRESS":{
        "p":0.8831168831,
        "r":0.9577464789,
        "f":0.9189189189
      },
      "ETHEREUMADDRESS":{
        "p":0.96,
        "r":0.96,
        "f":0.96
      },
      "PASSWORD":{
        "p":0.9791666667,
        "r":0.9527027027,
        "f":0.9657534247
      },
      "DISPLAYNAME":{
        "p":0.8673469388,
        "r":0.6488549618,
        "f":0.7423580786
      },
      "MAC":{
        "p":0.9375,
        "r":0.3260869565,
        "f":0.4838709677
      },
      "ORDINALDIRECTION":{
        "p":1.0,
        "r":0.6666666667,
        "f":0.8
      },
      "STREET":{
        "p":0.9090909091,
        "r":0.9090909091,
        "f":0.9090909091
      },
      "BIC":{
        "p":1.0,
        "r":1.0,
        "f":1.0
      },
      "CURRENCYAMOUNT":{
        "p":0.8333333333,
        "r":0.5,
        "f":0.625
      },
      "LASTNAME":{
        "p":1.0,
        "r":0.3333333333,
        "f":0.5
      },
      "CURRENCY_N":{
        "p":0.0,
        "r":0.0,
        "f":0.0
      },
      "MASKEDNUMBER":{
        "p":1.0,
        "r":0.3181818182,
        "f":0.4827586207
      },
      "NEARBYGPSCOORDINATE":{
        "p":1.0,
        "r":1.0,
        "f":1.0
      },
      "IBAN":{
        "p":1.0,
        "r":0.9411764706,
        "f":0.9696969697
      },
      "CREDITCARDCVV":{
        "p":1.0,
        "r":0.7142857143,
        "f":0.8333333333
      },
      "PIN":{
        "p":1.0,
        "r":0.8333333333,
        "f":0.9090909091
      },
      "LITECOINADDRESS":{
        "p":0.0,
        "r":0.0,
        "f":0.0
      },
      "CURRENCYSYMBOL":{
        "p":1.0,
        "r":0.75,
        "f":0.8571428571
      }
    },
    "tok2vec_loss":1080.5929883435,
    "ner_loss":950.6567382812
  }
}